{"status":"done","publicPath":"http://127.0.0.1:8080/","chunks":{"app":[{"name":"bundle.js","publicPath":"http://127.0.0.1:8080/bundle.js","path":"C:\\Workshop\\vuebank\\frontend\\dist\\bundle.js"},{"name":"app.d9f6cc1b649e00b5dc80.hot-update.js","publicPath":"http://127.0.0.1:8080/app.d9f6cc1b649e00b5dc80.hot-update.js","path":"C:\\Workshop\\vuebank\\frontend\\dist\\app.d9f6cc1b649e00b5dc80.hot-update.js"}]},"error":"ModuleBuildError","message":"Module build failed (from ./node_modules/eslint-loader/index.js):\nError: ENOENT: no such file or directory, open 'C:\\Workshop\\vuebank\\frontend\\src\\views\\Instrument.vue'"}