{"status":"done","publicPath":"http://127.0.0.1:8080/","chunks":{"app":[{"name":"bundle.js","publicPath":"http://127.0.0.1:8080/bundle.js","path":"C:\\Workshop\\vuebank\\frontend\\dist\\bundle.js"},{"name":"app.af7b6b9f4edf80f8282d.hot-update.js","publicPath":"http://127.0.0.1:8080/app.af7b6b9f4edf80f8282d.hot-update.js","path":"C:\\Workshop\\vuebank\\frontend\\dist\\app.af7b6b9f4edf80f8282d.hot-update.js"}]},"error":"ModuleBuildError","message":"Module build failed (from ./node_modules/eslint-loader/index.js):\nError: ENOENT: no such file or directory, open 'C:\\Workshop\\vuebank\\frontend\\src\\components\\Navbar.vue'"}